norijada_pdf/__init__.py
norijada_pdf/__main__.py
norijada_pdf/cli.py
norijada_pdf/fonts/Bangers-Regular.ttf
norijada_pdf/fonts/BebasNeue-Regular.ttf
norijada_pdf/fonts/BerkshireSwash-Regular.ttf
norijada_pdf/fonts/BlackOpsOne-Regular.ttf
norijada_pdf/fonts/Bungee-Regular.ttf
norijada_pdf/fonts/Courgette-Regular.ttf
norijada_pdf/fonts/Galindo-Regular.ttf
norijada_pdf/fonts/KaushanScript-Regular.ttf
norijada_pdf/fonts/LibreBaskerville-Regular.ttf
norijada_pdf/fonts/Lobster-Regular.ttf
norijada_pdf/fonts/MouseMemoirs-Regular.ttf
norijada_pdf/fonts/Pacifico-Regular.ttf
norijada_pdf/fonts/PatrickHand-Regular.ttf
norijada_pdf/fonts/Ranchers-Regular.ttf
norijada_pdf/fonts/RubikMonoOne-Regular.ttf
norijada_pdf/fonts/RussoOne-Regular.ttf
norijada_pdf/fonts/SigmarOne-Regular.ttf
norijada_pdf/fonts/Staatliches-Regular.ttf
norijada_pdf/main.py
norijada_pdf/settings.py
norijada_pdf-0.0.6.dist-info/entry_points.txt
norijada_pdf-0.0.6.dist-info/LICENSE
norijada_pdf-0.0.6.dist-info/METADATA
norijada_pdf-0.0.6.dist-info/WHEEL
norijada_pdf-0.0.6.dist-info/RECORD
