Metadata-Version: 2.1
Name: norijada-pdf
Version: 0.0.6
Summary: Utility for arranging short text in the PDF with minimum amount of empty space between text.
Author: marin
Author-email: marin.kruzic@gmail.com
Requires-Python: >=3.8,<4.0
Classifier: Programming Language :: Python :: 3
Classifier: Programming Language :: Python :: 3.8
Classifier: Programming Language :: Python :: 3.9
Classifier: Programming Language :: Python :: 3.10
Classifier: Programming Language :: Python :: 3.11
Requires-Dist: fpdf2 (>=2.6.1,<3.0.0)
Requires-Dist: rectpack (>=0.2.2,<0.3.0)
